nuvoton_isp/__init__.py
nuvoton_isp/cli.py
nuvoton_isp/isp.py
nuvoton_isp-0.1.3.dist-info/entry_points.txt
nuvoton_isp-0.1.3.dist-info/LICENSE
nuvoton_isp-0.1.3.dist-info/WHEEL
nuvoton_isp-0.1.3.dist-info/METADATA
nuvoton_isp-0.1.3.dist-info/RECORD
