Metadata-Version: 2.1
Name: nuvoton-isp
Version: 0.1.3
Summary: Nuvoton ISP library and CLI
Home-page: https://fishman.github.io/nuvoton_isp
License: MIT
Author: Reza Jelveh
Author-email: pypi@jelveh.me
Requires-Python: >=3.6
Classifier: Development Status :: 2 - Pre-Alpha
Classifier: Intended Audience :: Developers
Classifier: License :: OSI Approved :: MIT License
Classifier: Natural Language :: English
Classifier: Programming Language :: Python :: 3
Classifier: Programming Language :: Python :: 3.6
Classifier: Programming Language :: Python :: 3.7
Classifier: Programming Language :: Python :: 3.8
Classifier: Programming Language :: Python :: 3.9
Requires-Dist: click (>=7.1.2,<8.0.0)
Requires-Dist: pyusb (>=1.1.0,<2.0.0)
Project-URL: Repository, https://github.com/fishman/nuvoton_isp
